xlrd/__init__.py
xlrd/biffh.py
xlrd/book.py
xlrd/compdoc.py
xlrd/formatting.py
xlrd/formula.py
xlrd/info.py
xlrd/sheet.py
xlrd/timemachine.py
xlrd/xldate.py
xlrd/xlsx.py
xlrd_ignore_writeaccess_corruption-1.2.0.1.data/scripts/runxlrd.py
xlrd_ignore_writeaccess_corruption-1.2.0.1.dist-info/DESCRIPTION.rst
xlrd_ignore_writeaccess_corruption-1.2.0.1.dist-info/LICENSE.txt
xlrd_ignore_writeaccess_corruption-1.2.0.1.dist-info/METADATA
xlrd_ignore_writeaccess_corruption-1.2.0.1.dist-info/RECORD
xlrd_ignore_writeaccess_corruption-1.2.0.1.dist-info/WHEEL
xlrd_ignore_writeaccess_corruption-1.2.0.1.dist-info/metadata.json
xlrd_ignore_writeaccess_corruption-1.2.0.1.dist-info/top_level.txt
