Metadata-Version: 2.0
Name: xlrd-ignore-writeaccess-corruption
Version: 1.2.0.1
Summary: Library for developers to extract data from Microsoft Excel (tm) spreadsheet files
Home-page: https://github.com/djerbic/xlrd-ignore-writeaccess-corruption
Author: John Machin
Author-email: sjmachin@lexicon.net
License: BSD
Download-URL: https://github.com/djerbic/xlrd-ignore-writeaccess-corruption/archive/1.2.0.1.tar.gz
Keywords: xls,excel,spreadsheet,workbook
Platform: Any platform -- don't need Windows
Classifier: Development Status :: 5 - Production/Stable
Classifier: Intended Audience :: Developers
Classifier: License :: OSI Approved :: BSD License
Classifier: Programming Language :: Python
Classifier: Programming Language :: Python :: 2
Classifier: Programming Language :: Python :: 2.7
Classifier: Programming Language :: Python :: 3
Classifier: Programming Language :: Python :: 3.4
Classifier: Programming Language :: Python :: 3.5
Classifier: Programming Language :: Python :: 3.6
Classifier: Programming Language :: Python :: 3.7
Classifier: Operating System :: OS Independent
Classifier: Topic :: Database
Classifier: Topic :: Office/Business
Classifier: Topic :: Software Development :: Libraries :: Python Modules
